streamlit_merge_tables/app.py
streamlit_merge_tables/merge_executor.py
streamlit_merge_tables/streamlit_component/__init__.py
streamlit_merge_tables/streamlit_component/frontend/index.html
streamlit_merge_tables/streamlit_component/frontend/assets/index-DnSuP1vy.css
streamlit_merge_tables/streamlit_component/frontend/assets/index-KJ6kr4il.js
streamlit_merge_tables-1.0.4.dist-info/METADATA
streamlit_merge_tables-1.0.4.dist-info/WHEEL
streamlit_merge_tables-1.0.4.dist-info/entry_points.txt
streamlit_merge_tables-1.0.4.dist-info/top_level.txt
streamlit_merge_tables-1.0.4.dist-info/RECORD
