Metadata-Version: 2.4
Name: streamlit-merge-tables
Version: 1.0.4
Summary: Visual table merge tool for Streamlit
Author: Tuan Nguyen
Requires-Python: >=3.9
Requires-Dist: streamlit>=1.30
Requires-Dist: pandas
